{
    "@context": "http://schema.org",
    "@type": "Restaurant",
    "image": [
        "https://img.cdn4dd.com/cdn-cgi/image/fit=contain,width=1200,height=672,format=auto/https://doordash-static.s3.amazonaws.com/media/restaurant/cover/PeacefulRestaurant_Vancouver_BC.png",
        "https://img.cdn4dd.com/cdn-cgi/image/fit=contain,width=1200,height=672,format=auto/https://doordash-static.s3.amazonaws.com/media/store/header/5dae4495-d398-46bc-9c7e-419413e349d2.jpg"
    ],
    "name": "Peaceful Restaurant 和平饭店",
    "address": "2188 No 5 Rd #110, Richmond, BC V6X 2T1, Canada",
    "geo": {
        "@type": "GeoCoordinates",
        "latitude": "49.19568",
        "longitude": "-123.09111"
    },
    "priceRange": "$$",
    "hasMenu": {
        "@type": "Menu",
        "hasMenuSection": [
            [
                {
                    "name": "Most Ordered",
                    "hasMenuItem": [
                        {
                            "@type": "MenuItem",
                            "name": "A04. Peaceful Beef Rolls | 牛肉捲餅 ",
                            "description": "Four-spice beef rolled in a crispy green onion flat-bread and sweet hoisin sauce.",
                            "offers": {
                                "@type": "Offer",
                                "price": "CA$13.95"
                            },
                            "image": ""
                        },
                        {
                            "@type": "MenuItem",
                            "name": "K02. Dan-Dan Noodles | 擔擔麵 ",
                            "description": "Mild. Spicy and tangy Sichuan pepper peanut sauce, minced pork and spinach.",
                            "offers": {
                                "@type": "Offer",
                                "price": "CA$15.95"
                            },
                            "image": ""
                        },
                        {
                            "@type": "MenuItem",
                            "name": " L06. Stir-Fried Chicken Noodles | 雞肉炒麵",
                            "description": "Stir fried diced chicken with fresh assorted vegetables &amp; light soy sauce.",
                            "offers": {
                                "@type": "Offer",
                                "price": "CA$18.95"
                            },
                            "image": ""
                        },
                        {
                            "@type": "MenuItem",
                            "name": "A01.  Xiao-Long Bao Steamed Buns | 小籠包",
                            "description": "Thin buns filled with pork &amp; savoury juice steamed - 6pcs",
                            "offers": {
                                "@type": "Offer",
                                "price": "CA$11.95"
                            },
                            "image": ""
                        },
                        {
                            "@type": "MenuItem",
                            "name": "M01. Peaceful House Stir-Fried Rice | 和平炒飯",
                            "description": "Mild. Stir fried with diced pork, shrimp, egg, vegetables and cilantro - slightly spicy and chili garlic sauce.",
                            "offers": {
                                "@type": "Offer",
                                "price": "CA$19.95"
                            },
                            "image": ""
                        },
                        {
                            "@type": "MenuItem",
                            "name": "G04. Spicy Gingered Beef | 薑汁牛肉絲",
                            "description": "Spicy. Crispy shredded beef tossed in a spicy gingery sauce.",
                            "offers": {
                                "@type": "Offer",
                                "price": "CA$21.95"
                            },
                            "image": ""
                        },
                        {
                            "@type": "MenuItem",
                            "name": "E08. General Tso&apos;s Chicken | 左宗棠雞",
                            "description": "Mild. Crispy battered chicken tossed in a spicy tangy sauce.",
                            "offers": {
                                "@type": "Offer",
                                "price": "CA$21.95"
                            },
                            "image": ""
                        },
                        {
                            "@type": "MenuItem",
                            "name": "A16. Deep Fry Vegetarian Spring Roll | 炸素菜春卷 ",
                            "description": "Filled with mixed vegetable - 4pcs",
                            "offers": {
                                "@type": "Offer",
                                "price": "CA$11.95"
                            },
                            "image": ""
                        },
                        {
                            "@type": "MenuItem",
                            "name": "F01. Sweet &amp; Sour Pork| 咕嚕肉",
                            "description": "Crispy battered pork tossed in a tangy tomato-based sauce.",
                            "offers": {
                                "@type": "Offer",
                                "price": "CA$19.95"
                            },
                            "image": ""
                        },
                        {
                            "@type": "MenuItem",
                            "name": "L05. Shanghai Stir-Fried Noodles | 上海炒麵",
                            "description": "Shredded pork, cabbage and light soy sauce.",
                            "offers": {
                                "@type": "Offer",
                                "price": "CA$18.95"
                            },
                            "image": ""
                        },
                        {
                            "@type": "MenuItem",
                            "name": "M02. Yang-Zhou Stir-Fried Rice | 揚州炒飯",
                            "description": "Stir fried with diced BBQ pork, shrimp, egg and vegetables.",
                            "offers": {
                                "@type": "Offer",
                                "price": "CA$19.95"
                            },
                            "image": ""
                        },
                        {
                            "@type": "MenuItem",
                            "name": "A03. Pan-Fried Pork Buns | 生煎包",
                            "description": "Filled with pork and scallions, soft bun, crispy bottom - 5pcs",
                            "offers": {
                                "@type": "Offer",
                                "price": "CA$12.95"
                            },
                            "image": ""
                        }
                    ]
                },
                {
                    "name": "Dim Sum / 點心",
                    "hasMenuItem": [
                        {
                            "@type": "MenuItem",
                            "name": "A04. Peaceful Beef Rolls | 牛肉捲餅 ",
                            "description": "Four-spice beef rolled in a crispy green onion flat-bread and sweet hoisin sauce.",
                            "offers": {
                                "@type": "Offer",
                                "price": "CA$13.95"
                            },
                            "image": ""
                        },
                        {
                            "@type": "MenuItem",
                            "name": "A01.  Xiao-Long Bao Steamed Buns | 小籠包",
                            "description": "Thin buns filled with pork &amp; savoury juice steamed - 6pcs",
                            "offers": {
                                "@type": "Offer",
                                "price": "CA$11.95"
                            },
                            "image": ""
                        },
                        {
                            "@type": "MenuItem",
                            "name": "A03. Pan-Fried Pork Buns | 生煎包",
                            "description": "Filled with pork and scallions, soft bun, crispy bottom - 5pcs",
                            "offers": {
                                "@type": "Offer",
                                "price": "CA$12.95"
                            },
                            "image": ""
                        },
                        {
                            "@type": "MenuItem",
                            "name": "A12. Pan-Fried Chicken Dumplings | 雞肉鍋貼",
                            "description": "Filled with minced chicken and cabbage - 8 pcs.",
                            "offers": {
                                "@type": "Offer",
                                "price": "CA$12.95"
                            },
                            "image": ""
                        },
                        {
                            "@type": "MenuItem",
                            "name": "A11. Spicy Wontons in Chili Oil | 紅油抄手 ",
                            "description": "Mild. Little pork wontons tossed in Sichuan chili oil - 8 pcs.",
                            "offers": {
                                "@type": "Offer",
                                "price": "CA$11.95"
                            },
                            "image": ""
                        },
                        {
                            "@type": "MenuItem",
                            "name": "A10. Spicy &amp; Tangy Dumplings | 酸湯水餃 ",
                            "description": "Soft pork dumplings served in a spicy &amp; sour soup base - 8pcs",
                            "offers": {
                                "@type": "Offer",
                                "price": "CA$14.95"
                            },
                            "image": ""
                        },
                        {
                            "@type": "MenuItem",
                            "name": "A04. Peaceful Beef Rolls | 牛肉卷餅 ",
                            "description": "Five-spiced beef rolled in a crispy green onion flat-bread &amp; sweet hoisin sauce",
                            "offers": {
                                "@type": "Offer",
                                "price": "CA$13.95"
                            },
                            "image": ""
                        },
                        {
                            "@type": "MenuItem",
                            "name": "A14. Pan-Fried Vegetarian Dumplings  | 煎素菜鍋貼 ",
                            "description": "Filled with mixed vegetable &amp; cabbage - 8 pcs.",
                            "offers": {
                                "@type": "Offer",
                                "price": "CA$12.95"
                            },
                            "image": ""
                        },
                        {
                            "@type": "MenuItem",
                            "name": "A09. Mandarin Wonton Soup | 上海雲吞",
                            "description": "Pork and leafy green fillina, served in a light broth with shrimp flakes, spinach and nori seaweed - 8 pcs.",
                            "offers": {
                                "@type": "Offer",
                                "price": "CA$12.95"
                            },
                            "image": ""
                        },
                        {
                            "@type": "MenuItem",
                            "name": "A02.Steamed Soft Pork Buns | 狗不理包 ",
                            "description": "Soft yeasty bun with a pork filling - 5pcs",
                            "offers": {
                                "@type": "Offer",
                                "price": "CA$12.95"
                            },
                            "image": ""
                        },
                        {
                            "@type": "MenuItem",
                            "name": "A13. Pan-Fried Pork Dumplings | 豬肉鍋貼 ",
                            "description": "Filled with pork cabbage &amp; green onion - 8pc",
                            "offers": {
                                "@type": "Offer",
                                "price": "CA$12.95"
                            },
                            "image": ""
                        },
                        {
                            "@type": "MenuItem",
                            "name": "A17. Deep Fry Sesame Ball | 炸芝麻球 ",
                            "description": "Deep Fry Vegetarian Sesame Ball - 10pcs",
                            "offers": {
                                "@type": "Offer",
                                "price": "CA$10.95"
                            },
                            "image": ""
                        },
                        {
                            "@type": "MenuItem",
                            "name": "A08. Northern Pork Dumplings | 北方水餃",
                            "description": "Filled with pork,chives, cabbage, green onions, boiled - 8pcs",
                            "offers": {
                                "@type": "Offer",
                                "price": "CA$12.95"
                            },
                            "image": ""
                        },
                        {
                            "@type": "MenuItem",
                            "name": "A05. Peaceful Potato Rolls | 土豆絲卷餅 ",
                            "description": "Crispy flatbread rolled with shredded potato, scallions &amp; sweet hoisin sauce",
                            "offers": {
                                "@type": "Offer",
                                "price": "CA$11.95"
                            },
                            "image": ""
                        },
                        {
                            "@type": "MenuItem",
                            "name": "A06. Cumin Beef &amp; Flatbread | 孜然牛夾餅 ",
                            "description": "A sesame flat-bread filled with beef, cumin &amp; fresh hot peppers",
                            "offers": {
                                "@type": "Offer",
                                "price": "CA$13.95"
                            },
                            "image": ""
                        },
                        {
                            "@type": "MenuItem",
                            "name": "A09. Mandarin Wonton Soup | 上海雲吞",
                            "description": "Pork, watercress &amp; bokchoy filled wontons served in a light broth - 8pcs",
                            "offers": {
                                "@type": "Offer",
                                "price": "CA$12.95"
                            },
                            "image": ""
                        },
                        {
                            "@type": "MenuItem",
                            "name": "A15. Vegetarian Steamed Dumplings | 蒸素菜鍋貼 ",
                            "description": "Filled with vermicelli, bokchoy, tofu, mushroom &amp; carrot - 8pcs",
                            "offers": {
                                "@type": "Offer",
                                "price": "CA$12.95"
                            },
                            "image": ""
                        },
                        {
                            "@type": "MenuItem",
                            "name": "A16. Deep Fry Vegetarian Spring Roll | 炸素菜春卷 ",
                            "description": "Filled with mixed vegetable - 4pcs",
                            "offers": {
                                "@type": "Offer",
                                "price": "CA$11.95"
                            },
                            "image": ""
                        },
                        {
                            "@type": "MenuItem",
                            "name": "A07. Green Onion Pancakes | 葱油餅",
                            "description": "Mixed with green onions, salt and pan-fried - 2 pcs",
                            "offers": {
                                "@type": "Offer",
                                "price": "CA$10.95"
                            },
                            "image": ""
                        }
                    ]
                },
                {
                    "name": "Appetizers / 頭盤",
                    "hasMenuItem": [
                        {
                            "@type": "MenuItem",
                            "name": "B04. Barbecue Pork | 蜜汁又燒 ",
                            "description": "",
                            "offers": {
                                "@type": "Offer",
                                "price": "CA$14.95"
                            },
                            "image": ""
                        },
                        {
                            "@type": "MenuItem",
                            "name": "B07. Honey Garlic Chicken Wing | 蜜汁雞翅 ",
                            "description": "Crispy chicken wing tossed in a minced garlic &amp; honey sauce",
                            "offers": {
                                "@type": "Offer",
                                "price": "CA$14.95"
                            },
                            "image": ""
                        },
                        {
                            "@type": "MenuItem",
                            "name": "B05. Crispy Garlic Chicken Wing | 蒜香雞翅 ",
                            "description": "",
                            "offers": {
                                "@type": "Offer",
                                "price": "CA$14.95"
                            },
                            "image": ""
                        },
                        {
                            "@type": "MenuItem",
                            "name": "B02. Wood Ear Mushroom Salad | 涼拌木耳 ",
                            "description": "Tossed in a light soy-viegar dressing with cilantro and green onion",
                            "offers": {
                                "@type": "Offer",
                                "price": "CA$12.95"
                            },
                            "image": ""
                        },
                        {
                            "@type": "MenuItem",
                            "name": "B06. Salt &amp; Pepper Chicken Wing (S) | 椒鹽雞翅 (細)",
                            "description": "Crispy chicken wing tossed in spiced salt &amp; diced chilli pepper",
                            "offers": {
                                "@type": "Offer",
                                "price": "CA$14.95"
                            },
                            "image": ""
                        },
                        {
                            "@type": "MenuItem",
                            "name": "B08. Deep Fried Chicken Wing | 酥炸雞翅 ",
                            "description": "",
                            "offers": {
                                "@type": "Offer",
                                "price": "CA$14.95"
                            },
                            "image": ""
                        },
                        {
                            "@type": "MenuItem",
                            "name": "B03. Fried Crispy Tofu | 香脆豆腐 ",
                            "description": "Crispy tofu tossed in salt ",
                            "offers": {
                                "@type": "Offer",
                                "price": "CA$12.95"
                            },
                            "image": ""
                        },
                        {
                            "@type": "MenuItem",
                            "name": "B01. Sichuan Cucumbers | 麻辣黃瓜 ",
                            "description": "Fresh Cucumbers tossed in a spicy Sichuan peppercorn dressing &amp; garlic",
                            "offers": {
                                "@type": "Offer",
                                "price": "CA$12.95"
                            },
                            "image": ""
                        }
                    ]
                },
                {
                    "name": "Soup / 湯",
                    "hasMenuItem": [
                        {
                            "@type": "MenuItem",
                            "name": "C11. Wonton Soup (S) | 雲吞湯 (細) ",
                            "description": "",
                            "offers": {
                                "@type": "Offer",
                                "price": "CA$14.95"
                            },
                            "image": ""
                        },
                        {
                            "@type": "MenuItem",
                            "name": "C01. Sichuan Hot &amp; Sour Soup (S) | 四川酸辣湯 (細)",
                            "description": "Pork, shrimp, bamboo, carrot, woodear, mushroom &amp; egg in a spicy",
                            "offers": {
                                "@type": "Offer",
                                "price": "CA$14.95"
                            },
                            "image": ""
                        },
                        {
                            "@type": "MenuItem",
                            "name": "C07. Tomato Egg Soup (S) |蕃茄蛋湯 (細)",
                            "description": "Fresh tomato &amp; threaded egg simmered in a light broth",
                            "offers": {
                                "@type": "Offer",
                                "price": "CA$14.95"
                            },
                            "image": ""
                        },
                        {
                            "@type": "MenuItem",
                            "name": "C03. Minced Chicken with Corn Soup (S) | 雞蓉粟米羹 (細)",
                            "description": "Minced chicken, sweet corn soup.",
                            "offers": {
                                "@type": "Offer",
                                "price": "CA$14.95"
                            },
                            "image": ""
                        },
                        {
                            "@type": "MenuItem",
                            "name": "C09. Vegetarian Tofu Soup (S) | 素豆腐湯 (細)",
                            "description": "Vegetarian, tofu soup.",
                            "offers": {
                                "@type": "Offer",
                                "price": "CA$14.95"
                            },
                            "image": ""
                        },
                        {
                            "@type": "MenuItem",
                            "name": "C05. Seafood Tofu Soup (S) | 海鮮豆腐羹 (細)",
                            "description": "Fish, prawn, squid, soft tofu and egg white in a clear broth",
                            "offers": {
                                "@type": "Offer",
                                "price": "CA$14.95"
                            },
                            "image": ""
                        }
                    ]
                },
                {
                    "name": "Seafood / 海鮮",
                    "hasMenuItem": [
                        {
                            "@type": "MenuItem",
                            "name": "D03. Salted and Pepper Squid | 椒鹽鮮魷 ",
                            "description": "Mild. Crispy squid tossed in spiced salt and diced chili pepper.\n",
                            "offers": {
                                "@type": "Offer",
                                "price": "CA$22.95"
                            },
                            "image": ""
                        },
                        {
                            "@type": "MenuItem",
                            "name": "D09. Kung Pao Prawn | 宮保蝦球",
                            "description": "",
                            "offers": {
                                "@type": "Offer",
                                "price": "CA$22.95"
                            },
                            "image": ""
                        },
                        {
                            "@type": "MenuItem",
                            "name": "D01. Sichuan Broth Braised Fish | 水煮魚片 ",
                            "description": "Sliced basa braised in a spicy Sichuan peppercorn broth &amp; chili oil, served on a bed of greens",
                            "offers": {
                                "@type": "Offer",
                                "price": "CA$22.95"
                            },
                            "image": ""
                        },
                        {
                            "@type": "MenuItem",
                            "name": "D05. Spicy Chili-Garlic Prawns | 干燒明蝦 ",
                            "description": "Mild. Battered prawns stir-fried with diced peppers &amp; chilli-garlic sauce",
                            "offers": {
                                "@type": "Offer",
                                "price": "CA$22.95"
                            },
                            "image": ""
                        },
                        {
                            "@type": "MenuItem",
                            "name": "D06. Crispy Prawns Meat | 香脆蝦仁 ",
                            "description": "",
                            "offers": {
                                "@type": "Offer",
                                "price": "CA$22.95"
                            },
                            "image": ""
                        },
                        {
                            "@type": "MenuItem",
                            "name": "D08. Pan Fried Shrimp, Squid &amp; Fillets | 油泡三鮮 ",
                            "description": "",
                            "offers": {
                                "@type": "Offer",
                                "price": "CA$22.95"
                            },
                            "image": ""
                        },
                        {
                            "@type": "MenuItem",
                            "name": "D02. Spicy Chilli-Garlic Fish | 干燒魚塊",
                            "description": "Crispy basa fish tossed in a chili garlic sauce",
                            "offers": {
                                "@type": "Offer",
                                "price": "CA$22.95"
                            },
                            "image": ""
                        },
                        {
                            "@type": "MenuItem",
                            "name": "D04. Spicy Chili Squid | 麻辣鮮魷 ",
                            "description": "Medium. Stir fried with green peppers &amp; tongue tingling peppercorn.",
                            "offers": {
                                "@type": "Offer",
                                "price": "CA$22.95"
                            },
                            "image": ""
                        },
                        {
                            "@type": "MenuItem",
                            "name": "D07. Prawns &amp; Braised Tofu | 蝦仁豆腐 ",
                            "description": "Soft tofu &amp; prawns meat served in a light and clear sauce",
                            "offers": {
                                "@type": "Offer",
                                "price": "CA$22.95"
                            },
                            "image": ""
                        }
                    ]
                },
                {
                    "name": "Pork / 豬肉",
                    "hasMenuItem": [
                        {
                            "@type": "MenuItem",
                            "name": "F01. Sweet &amp; Sour Pork| 咕嚕肉",
                            "description": "Crispy battered pork tossed in a tangy tomato-based sauce.",
                            "offers": {
                                "@type": "Offer",
                                "price": "CA$19.95"
                            },
                            "image": ""
                        },
                        {
                            "@type": "MenuItem",
                            "name": "F05. Sweet Soy Glazed Spareribs | 糖醋排骨",
                            "description": "Spareribs tossed in a reduced sweet soy and ginger sauce.",
                            "offers": {
                                "@type": "Offer",
                                "price": "CA$20.95"
                            },
                            "image": ""
                        },
                        {
                            "@type": "MenuItem",
                            "name": "F06. Honey Garlic Spareribs | 蜜汁排骨 ",
                            "description": "Crispy spareribs tossed in a minced garlic and honey sauce.",
                            "offers": {
                                "@type": "Offer",
                                "price": "CA$20.95"
                            },
                            "image": ""
                        },
                        {
                            "@type": "MenuItem",
                            "name": "F11. Sichuan String Beans | 干煸四季豆",
                            "description": "Stir-fried with a bit of pork, garlic, crushed chillies &amp; soy sauce",
                            "offers": {
                                "@type": "Offer",
                                "price": "CA$18.95"
                            },
                            "image": ""
                        },
                        {
                            "@type": "MenuItem",
                            "name": "F07. Salted and Pepper Pork Ribs | 椒鹽排骨",
                            "description": "Mild. crispy pork ribs tossed in spiced salt &amp; diced chili pepper.",
                            "offers": {
                                "@type": "Offer",
                                "price": "CA$20.95"
                            },
                            "image": ""
                        },
                        {
                            "@type": "MenuItem",
                            "name": "F02. Mandarin Mu-Shu Shredded Pork | 北方木須肉 ",
                            "description": "Stir-fried with shredded woodear mushroom, egg &amp; cabbage",
                            "offers": {
                                "@type": "Offer",
                                "price": "CA$19.95"
                            },
                            "image": ""
                        },
                        {
                            "@type": "MenuItem",
                            "name": "F04. Chili-Garlic Sauce Shredded Pork | 魚香肉絲 ",
                            "description": "Stir-fried with shredded woodear fungus and bamboo shoot",
                            "offers": {
                                "@type": "Offer",
                                "price": "CA$19.95"
                            },
                            "image": ""
                        },
                        {
                            "@type": "MenuItem",
                            "name": "F10. Chili-Garlic Eggplant | 魚香茄子",
                            "description": "Sautéed with shredded pork, bamboo, woodear mushroom &amp; chili paste",
                            "offers": {
                                "@type": "Offer",
                                "price": "CA$18.95"
                            },
                            "image": ""
                        },
                        {
                            "@type": "MenuItem",
                            "name": "F08. Dry Garlic Pork | 蒜子干豬",
                            "description": "",
                            "offers": {
                                "@type": "Offer",
                                "price": "CA$19.95"
                            },
                            "image": ""
                        },
                        {
                            "@type": "MenuItem",
                            "name": "F09. Sichuan Mah-Po Tofu | 麻婆豆腐 ",
                            "description": "Soft tofu cooked with minced pork &amp; peppercorn sauce",
                            "offers": {
                                "@type": "Offer",
                                "price": "CA$18.95"
                            },
                            "image": ""
                        },
                        {
                            "@type": "MenuItem",
                            "name": "F03. Beijing Sweet Bean Sauce Pork | 京醬肉絲",
                            "description": "Sweet-savory pork served on a bed of shredded green onions.",
                            "offers": {
                                "@type": "Offer",
                                "price": "CA$20.95"
                            },
                            "image": ""
                        }
                    ]
                },
                {
                    "name": "Chicken / 雞肉",
                    "hasMenuItem": [
                        {
                            "@type": "MenuItem",
                            "name": "E08. General Tso&apos;s Chicken | 左宗棠雞",
                            "description": "Mild. Crispy battered chicken tossed in a spicy tangy sauce.",
                            "offers": {
                                "@type": "Offer",
                                "price": "CA$21.95"
                            },
                            "image": ""
                        },
                        {
                            "@type": "MenuItem",
                            "name": "E09. Sweet and Sour Chicken | 咕嚕雞球",
                            "description": "Crispy battered chicken tossed in a tangy tomato-based sauce.",
                            "offers": {
                                "@type": "Offer",
                                "price": "CA$21.95"
                            },
                            "image": ""
                        },
                        {
                            "@type": "MenuItem",
                            "name": "E03. Sweet Soy Glazed Chicken | 糖醋雞丁 ",
                            "description": "Crispy chicken tossed in a reduced sweet soy sauce with ginger &amp; garlic",
                            "offers": {
                                "@type": "Offer",
                                "price": "CA$21.95"
                            },
                            "image": ""
                        },
                        {
                            "@type": "MenuItem",
                            "name": "E13. Sesame Chicken | 芝麻雞",
                            "description": "Crispy chicken tossed in a reduced sweet soy sauce with ginger &amp; garlic and Sesame",
                            "offers": {
                                "@type": "Offer",
                                "price": "CA$21.95"
                            },
                            "image": ""
                        },
                        {
                            "@type": "MenuItem",
                            "name": "E05. Curry Chicken | 咖哩雞 ",
                            "description": "Yellow curry, sweet bell peppers &amp; onions",
                            "offers": {
                                "@type": "Offer",
                                "price": "CA$21.95"
                            },
                            "image": ""
                        },
                        {
                            "@type": "MenuItem",
                            "name": "E04. Kung Pao Chicken | 宮保雞丁",
                            "description": "Mild. Sweet bell peppers, onions, peanuts and chili peppers.",
                            "offers": {
                                "@type": "Offer",
                                "price": "CA$21.95"
                            },
                            "image": ""
                        },
                        {
                            "@type": "MenuItem",
                            "name": "E14. Black Bean Sauce Chicken | 鼓汁雞球",
                            "description": "Chicken stir fried with onions and bell peppers in black bean sauce.",
                            "offers": {
                                "@type": "Offer",
                                "price": "CA$21.95"
                            },
                            "image": ""
                        },
                        {
                            "@type": "MenuItem",
                            "name": "E01. Sichuan Thousand Chili Chicken | 四川辣子雞",
                            "description": "Medium. Crispy chicken stir fried with dried peppers, tongue-tingling peppercorns, garlic, ginger and green onion.",
                            "offers": {
                                "@type": "Offer",
                                "price": "CA$21.95"
                            },
                            "image": ""
                        },
                        {
                            "@type": "MenuItem",
                            "name": "E07. Chicken &amp; Seasonal Vegetables | 雜菜雞丁 ",
                            "description": "Stir-fried with minced garlic &amp; touch of soy sauce",
                            "offers": {
                                "@type": "Offer",
                                "price": "CA$21.95"
                            },
                            "image": ""
                        },
                        {
                            "@type": "MenuItem",
                            "name": "E11. Honey Garlic Chicken Wing | 蜜汁雞翅 ",
                            "description": "Crispy chicken wing tossed in a minced garlic &amp; honey sauce",
                            "offers": {
                                "@type": "Offer",
                                "price": "CA$21.95"
                            },
                            "image": ""
                        },
                        {
                            "@type": "MenuItem",
                            "name": "E12. Deep Fried Chicken Wing | 酥炸雞翅 ",
                            "description": "",
                            "offers": {
                                "@type": "Offer",
                                "price": "CA$21.95"
                            },
                            "image": ""
                        },
                        {
                            "@type": "MenuItem",
                            "name": "E15. Mandarin Orange Ginger Chicken | 橙汁姜雞",
                            "description": "Mild spicy. crispy battered chicken tossed in sweet &amp; spicy orange-ginger sauce.",
                            "offers": {
                                "@type": "Offer",
                                "price": "CA$21.95"
                            },
                            "image": ""
                        },
                        {
                            "@type": "MenuItem",
                            "name": "E10. Salt &amp; Pepper Chicken Wing (L) | 椒鹽雞翅 (大)",
                            "description": "",
                            "offers": {
                                "@type": "Offer",
                                "price": "CA$21.95"
                            },
                            "image": ""
                        },
                        {
                            "@type": "MenuItem",
                            "name": "E06. Chicken &amp; Broccoli | 雞球百加利",
                            "description": "Stir-fried with minced garlic and light soy sauce.",
                            "offers": {
                                "@type": "Offer",
                                "price": "CA$21.95"
                            },
                            "image": ""
                        },
                        {
                            "@type": "MenuItem",
                            "name": "E02. Green Peppered Chicken | 尖椒雞丁 ",
                            "description": "Crispy chicken stir-fried with fresh jalapenos, peppercorn oil &amp; garlic",
                            "offers": {
                                "@type": "Offer",
                                "price": "CA$21.95"
                            },
                            "image": ""
                        }
                    ]
                },
                {
                    "name": "Beef / 牛肉",
                    "hasMenuItem": [
                        {
                            "@type": "MenuItem",
                            "name": "G07. Black Bean Sauce Beef | 豉椒牛肉 \t",
                            "description": "Beef stir fried with onions and bell peppers in black bean sauce.",
                            "offers": {
                                "@type": "Offer",
                                "price": "CA$20.95"
                            },
                            "image": ""
                        },
                        {
                            "@type": "MenuItem",
                            "name": "G03. Xin-Jiang Cumin Beef | 孜然牛肉 ",
                            "description": "Stir fried with fresh peppers, cumin chili flakes",
                            "offers": {
                                "@type": "Offer",
                                "price": "CA$21.95"
                            },
                            "image": ""
                        },
                        {
                            "@type": "MenuItem",
                            "name": "G05. Beef &amp; Broccoli | 百加利牛肉 ",
                            "description": "Stir-fried with minced garlic and light soy sauce.",
                            "offers": {
                                "@type": "Offer",
                                "price": "CA$21.95"
                            },
                            "image": ""
                        },
                        {
                            "@type": "MenuItem",
                            "name": "G02. Green Onion Beef | 葱爆牛肉",
                            "description": "Tender beef rapidly stir-fried with green onions &amp; ginger",
                            "offers": {
                                "@type": "Offer",
                                "price": "CA$21.95"
                            },
                            "image": ""
                        },
                        {
                            "@type": "MenuItem",
                            "name": "G06. Stir Fried Beef with Seasonal Vegetables | 雜菜炒牛肉",
                            "description": "",
                            "offers": {
                                "@type": "Offer",
                                "price": "CA$21.95"
                            },
                            "image": ""
                        },
                        {
                            "@type": "MenuItem",
                            "name": "G04. Spicy Gingered Beef | 薑汁牛肉絲",
                            "description": "Spicy. Crispy shredded beef tossed in a spicy gingery sauce.",
                            "offers": {
                                "@type": "Offer",
                                "price": "CA$21.95"
                            },
                            "image": ""
                        },
                        {
                            "@type": "MenuItem",
                            "name": "G01. Sichuan Broth Braised Beef | 水煮牛肉片 ",
                            "description": "Sliced beef braised in a spicy Sichuan peppercorn broth &amp; chili oil, served on a bed of greens",
                            "offers": {
                                "@type": "Offer",
                                "price": "CA$22.95"
                            },
                            "image": ""
                        }
                    ]
                },
                {
                    "name": "Vegetable / 蔬菜",
                    "hasMenuItem": [
                        {
                            "@type": "MenuItem",
                            "name": "H06. Sichuan Stir-fried A-Choy | 熗炒油麥菜 ",
                            "description": "Crispy leafy greens stir-fried with garlic, malt vinegar &amp; Sichuan peppercorns oil",
                            "offers": {
                                "@type": "Offer",
                                "price": "CA$18.95"
                            },
                            "image": ""
                        },
                        {
                            "@type": "MenuItem",
                            "name": "H10. Garlic String Beans | 蒜蓉四季豆 ",
                            "description": "Lightly stir-fried with minced garlic",
                            "offers": {
                                "@type": "Offer",
                                "price": "CA$18.95"
                            },
                            "image": ""
                        },
                        {
                            "@type": "MenuItem",
                            "name": "H08. Chinese Ratatouille | 地三鮮 ",
                            "description": "Eggplant, green peppers &amp; potatoes stir-fried with a savoury garlic sauce",
                            "offers": {
                                "@type": "Offer",
                                "price": "CA$18.95"
                            },
                            "image": ""
                        },
                        {
                            "@type": "MenuItem",
                            "name": "H04. Tangy Shredded Potato | 醋溜土豆絲",
                            "description": "Lightly stir-fried with minced garlic.",
                            "offers": {
                                "@type": "Offer",
                                "price": "CA$17.95"
                            },
                            "image": ""
                        }
                    ]
                }
            ]
        ]
    },
    "review": [
        {
            "@type": "Review",
            "publisher": "DoorDash",
            "author": {
                "@type": "Person",
                "name": "Kevin H"
            },
            "reviewRating": {
                "worstRating": 1,
                "bestRating": 5,
                "ratingValue": 4
            },
            "reviewBody": "Good food but item said 5 A04. Peaceful Beef Rolls | 牛肉卷餅  but only received 4. Bit expensive for just four. "
        },
        {
            "@type": "Review",
            "publisher": "DoorDash",
            "author": {
                "@type": "Person",
                "name": "Marcia H"
            },
            "reviewRating": {
                "worstRating": 1,
                "bestRating": 5,
                "ratingValue": 3
            },
            "reviewBody": "Beg rolls were delicious. Other dishes so-so. General Tso&apos;s chicken not as expected. Bland snd sticky"
        },
        {
            "@type": "Review",
            "publisher": "DoorDash",
            "author": {
                "@type": "Person",
                "name": "Jamie A"
            },
            "reviewRating": {
                "worstRating": 1,
                "bestRating": 5,
                "ratingValue": 3
            },
            "reviewBody": "the mah-poh tofu and Shanghai noodles did not taste consistent with other Peaceful restaurant locations, which left us disappointed. We choose Peaceful restaurant because we trust that our experience will be consistent regardless of location."
        },
        {
            "@type": "Review",
            "publisher": "DoorDash",
            "author": {
                "@type": "Person",
                "name": "Rachel L"
            },
            "reviewRating": {
                "worstRating": 1,
                "bestRating": 5,
                "ratingValue": 3
            },
            "reviewBody": "ordered fried crispy tofu in salty egg yolk, but could not taste the salted egg yolk flavor at all and the dish itself was very bland."
        },
        {
            "@type": "Review",
            "publisher": "DoorDash",
            "author": {
                "@type": "Person",
                "name": "Jeffrey E"
            },
            "reviewRating": {
                "worstRating": 1,
                "bestRating": 5,
                "ratingValue": 2
            },
            "reviewBody": "The sweet and sour chicken, and general tso&apos;s chicken from peaceful Richmond tastes NOTHING like the dishes from the peaceful restaraunts in Vancouver. I love peaceful in Vancouver, but their Richmond location doesn&apos;t taste good and is nothing like it. They also don&apos;t have mushu noodle or cumin lamb noodle on the menu. Such a shame. "
        }
    ],
    "aggregateRating": {
        "@type": "AggregateRating",
        "ratingCount": 50,
        "worstRating": 1,
        "bestRating": 5,
        "reviewCount": 50,
        "ratingValue": 4.3
    },
    "servesCuisine": [
        "Vegetarian",
        "Noodles",
        "Fried Rice",
        "Dim Sum",
        "Chicken",
        "Chinese"
    ],
    "url": "https://www.doordash.com/store/peaceful-restaurant-和平饭店-richmond-2579242/?cursor=eyJzZWFyY2hfaXRlbV9jYXJvdXNlbF9jdXJzb3IiOnsicXVlcnkiOiJyZXN0YXVyYW50cyIsIml0ZW1faWRzIjpbXSwic2VhcmNoX3Rlcm0iOiJyZXN0YXVyYW50IiwidmVydGljYWxfaWQiOi05OSwidmVydGljYWxfbmFtZSI6IiJ9LCJzdG9yZV9wcmltYXJ5X3ZlcnRpY2FsX2lkcyI6WzEsNF19&pickup=false",
    "phone": "+16043708726",
    "doordashOperationHourInfo": {
        "MONDAY": [
            "11 AM - 2:40 PM\",\"5 PM - 8:40 PM"
        ],
        "TUESDAY": [
            "11 AM - 2:40 PM\",\"5 PM - 8:40 PM"
        ],
        "THURSDAY": [
            "11 AM - 2:40 PM\",\"5 PM - 8:40 PM"
        ],
        "FRIDAY": [
            "11 AM - 2:40 PM\",\"5 PM - 8:40 PM"
        ],
        "SATURDAY": [
            "11 AM - 2:40 PM\",\"5 PM - 8:40 PM"
        ],
        "SUNDAY": [
            "11 AM - 2:40 PM\",\"5 PM - 8:40 PM"
        ]
    },
    "storeOperationHourInfo": {
        "MONDAY": [
            "11 AM - 3 PM\",\"5 PM - 9 PM"
        ],
        "TUESDAY": [
            "11 AM - 3 PM\",\"5 PM - 9 PM"
        ],
        "THURSDAY": [
            "11 AM - 3 PM\",\"5 PM - 9 PM"
        ],
        "FRIDAY": [
            "11 AM - 3 PM\",\"5 PM - 9 PM"
        ],
        "SATURDAY": [
            "11 AM - 3 PM\",\"5 PM - 9 PM"
        ],
        "SUNDAY": [
            "11 AM - 3 PM\",\"5 PM - 9 PM"
        ]
    },
    "merchant_cuisine": "Not found"
}